damnsshmanager/__init__.py
damnsshmanager/cli.py
damnsshmanager/config.py
damnsshmanager/connect.py
damnsshmanager/damnfiles/messages.ini
damnsshmanager/hosts.py
damnsshmanager/localtunnel.py
damnsshmanager/messages.py
damnsshmanager/ssh/__init__.py
damnsshmanager/ssh/channel.py
damnsshmanager/ssh/native.py
damnsshmanager/ssh/paramiko.py
damnsshmanager/ssh/provider.py
damnsshmanager/ssh/test.py
damnsshmanager/storage.py
damnsshmanager-0.2.4.dist-info/entry_points.txt
damnsshmanager-0.2.4.dist-info/LICENSE.txt
damnsshmanager-0.2.4.dist-info/WHEEL
damnsshmanager-0.2.4.dist-info/METADATA
damnsshmanager-0.2.4.dist-info/RECORD
