Metadata-Version: 2.1
Name: damnsshmanager
Version: 0.2.4
Summary: The simplest ssh cli agent one is able to find
License: GNU GPLv3
Author: Nils Verheyen
Author-email: nils@ungerichtet.de
Requires-Python: >=3.8,<4.0
Classifier: License :: Other/Proprietary License
Classifier: Programming Language :: Python :: 3
Classifier: Programming Language :: Python :: 3.10
Classifier: Programming Language :: Python :: 3.8
Classifier: Programming Language :: Python :: 3.9
Requires-Dist: appdirs (>=1.4.4,<2.0.0)
Requires-Dist: loguru (>=0.5.3,<0.6.0)
Requires-Dist: paramiko (>=2.8.0,<3.0.0)
Requires-Dist: sshtunnel (>=0.4.0,<0.5.0)
